app_skellington/__init__.py
app_skellington/_bootstrap.py
app_skellington/_util.py
app_skellington/_version.py
app_skellington/app_container.py
app_skellington/cfg.py
app_skellington/cli.py
app_skellington/log.py
app_skellington/version.py
app_skellington-0.2.2.dist-info/LICENSE.txt
app_skellington-0.2.2.dist-info/METADATA
app_skellington-0.2.2.dist-info/WHEEL
app_skellington-0.2.2.dist-info/top_level.txt
app_skellington-0.2.2.dist-info/RECORD
