Metadata-Version: 2.1
Name: app_skellington
Version: 0.2.2
Summary: app_skellington CLI framework
Author-email: Mathew Guest <mat@zavage.net>
License: App Skellington
Project-URL: homepage, https://zavage-software.com/portfolio/app_skellington
Project-URL: repository, https://git-repos.zavage.net/Zavage-Software/app_skellington
Project-URL: documentation, https://git-repos.zavage.net/Zavage-Software/app_skellington
Keywords: cli,logging,application
Classifier: Programming Language :: Python :: 3
Classifier: License :: OSI Approved :: MIT License
Classifier: Operating System :: OS Independent
Requires-Python: >=3.8
License-File: LICENSE.txt
Requires-Dist: appdirs
Requires-Dist: configobj
Requires-Dist: colorlog
Provides-Extra: dev
Requires-Dist: black ; extra == 'dev'
Requires-Dist: pre-commit ; extra == 'dev'
Requires-Dist: isort ; extra == 'dev'
Requires-Dist: flake8 ; extra == 'dev'
